pnu_prep-1.0.3.data/data/etc/eign
pnu_prep-1.0.3.data/data/man/man1/prep.1.gz
prep/__init__.py
prep/main.py
pnu_prep-1.0.3.dist-info/License
pnu_prep-1.0.3.dist-info/METADATA
pnu_prep-1.0.3.dist-info/WHEEL
pnu_prep-1.0.3.dist-info/entry_points.txt
pnu_prep-1.0.3.dist-info/top_level.txt
pnu_prep-1.0.3.dist-info/RECORD
